Metadata-Version: 2.4
Name: orcaagent-cli
Version: 2.0.7
Summary: CLI for interacting with orcaagent API
Project-URL: Repository, https://git.woa.com/OrcaAgent/OrcaAgent-Cli
License: MIT
Requires-Python: >=3.11
Requires-Dist: aiohttp<4.0.0,>=3.8.3
Requires-Dist: click>=8.1.7
Requires-Dist: langchain-community>=0.3.29
Requires-Dist: langchain-core>=0.3.76
Requires-Dist: langchain>=0.3.27
Requires-Dist: langgraph-sdk>=0.2.0; python_version >= '3.11'
Requires-Dist: langgraph>=1.0.0
Requires-Dist: langsmith>=0.3.45
Requires-Dist: orcakit-runner-inmem>=0.0.1
Requires-Dist: orcakit-runner>=0.0.1
Requires-Dist: pydantic<3.0.0,>=2.7.4
Requires-Dist: python-dotenv>=1.0.0
Requires-Dist: requests<3,>=2.0
Requires-Dist: rich>=13.9.4
Requires-Dist: typing-extensions<5,>=4.10
Provides-Extra: inmem
Requires-Dist: python-dotenv>=0.8.0; extra == 'inmem'
